thot.cp312-win32.pyd
thot/__init__.pyi
thot/py.typed
thot/alignment/__init__.pyi
thot/common/__init__.pyi
thot/translation/__init__.pyi
sil_thot-3.4.7.dist-info/AUTHORS
sil_thot-3.4.7.dist-info/COPYING.LESSER
sil_thot-3.4.7.dist-info/METADATA
sil_thot-3.4.7.dist-info/WHEEL
sil_thot-3.4.7.dist-info/top_level.txt
sil_thot-3.4.7.dist-info/RECORD
