Metadata-Version: 2.1
Name: sil-thot
Version: 3.4.7
Summary: A toolkit for statistical word alignment and machine translation
Home-page: https://github.com/sillsdev/thot
Author: SIL International
Maintainer: Damien Daspit
Maintainer-email: damien_daspit@sil.org
License: LGPL-3.0
Project-URL: Repository, https://github.com/sillsdev/thot
Keywords: statistical machine translation word alignment natural language processing
Platform: Windows
Platform: macOS
Platform: Linux
Classifier: License :: OSI Approved :: GNU Lesser General Public License v3 (LGPLv3)
Classifier: Programming Language :: Python :: 3
Classifier: Programming Language :: Python :: 3.8
Classifier: Programming Language :: Python :: 3.9
Classifier: Programming Language :: Python :: 3.10
Classifier: Programming Language :: Python :: 3.11
Classifier: Programming Language :: Python :: 3.12
Classifier: Topic :: Scientific/Engineering
Classifier: Topic :: Scientific/Engineering :: Artificial Intelligence
Classifier: Topic :: Scientific/Engineering :: Mathematics
Classifier: Topic :: Software Development
Classifier: Topic :: Software Development :: Libraries
Classifier: Topic :: Software Development :: Libraries :: Python Modules
Classifier: Topic :: Text Processing
Classifier: Topic :: Text Processing :: Linguistic
Requires-Python: >=3.8, <4.0
License-File: COPYING.LESSER
License-File: AUTHORS
Provides-Extra: test
Requires-Dist: pytest; extra == "test"
Requires-Dist: numpy; extra == "test"
